ChromeDoc/README.md
ChromeDoc/__init__.py
ChromeDoc/__main__.py
ChromeDoc/file.epub
ChromeDoc/index.html
ChromeDoc/css/__init__.py
ChromeDoc/css/annotations.css
ChromeDoc/css/main.css
ChromeDoc/css/normalize.css
ChromeDoc/css/popup.css
ChromeDoc/font/__init__.py
ChromeDoc/font/fontello.eot
ChromeDoc/font/fontello.svg
ChromeDoc/font/fontello.ttf
ChromeDoc/font/fontello.woff
ChromeDoc/img/__init__.py
ChromeDoc/img/annotator-glyph-sprite.png
ChromeDoc/img/annotator-icon-sprite.png
ChromeDoc/img/apple-touch-icon.png
ChromeDoc/img/cancelfullscreen.png
ChromeDoc/img/close.png
ChromeDoc/img/fullscreen.png
ChromeDoc/img/loader.gif
ChromeDoc/img/menu-icon.png
ChromeDoc/img/save.png
ChromeDoc/img/saved.png
ChromeDoc/img/settings-s.png
ChromeDoc/img/settings.png
ChromeDoc/img/star.png
ChromeDoc/js/__init__.py
ChromeDoc/js/epub.js
ChromeDoc/js/epub.min.js
ChromeDoc/js/epub.min.map
ChromeDoc/js/hooks.min.js
ChromeDoc/js/hooks.min.map
ChromeDoc/js/reader.js
ChromeDoc/js/reader.js.map
ChromeDoc/js/reader.min.js
ChromeDoc/js/reader.min.map
ChromeDoc/js/hooks/__init__.py
ChromeDoc/js/hooks/extensions/__init__.py
ChromeDoc/js/hooks/extensions/highlight.js
ChromeDoc/js/libs/__init__.py
ChromeDoc/js/libs/jquery.min.js
ChromeDoc/js/libs/localforage.min.js
ChromeDoc/js/libs/screenfull.js
ChromeDoc/js/libs/screenfull.min.js
ChromeDoc/js/libs/zip.min.js
ChromeDoc/js/plugins/__init__.py
ChromeDoc/js/plugins/hypothesis.js
ChromeDoc/js/plugins/search.js
chrome_doc-2024.3.2.0.dist-info/METADATA
chrome_doc-2024.3.2.0.dist-info/WHEEL
chrome_doc-2024.3.2.0.dist-info/entry_points.txt
chrome_doc-2024.3.2.0.dist-info/top_level.txt
chrome_doc-2024.3.2.0.dist-info/RECORD
